tests/__init__.py
tests/test_yamlenv.py
yamlenv/__init__.py
yamlenv-0.1.dist-info/top_level.txt
yamlenv-0.1.dist-info/DESCRIPTION.rst
yamlenv-0.1.dist-info/METADATA
yamlenv-0.1.dist-info/metadata.json
yamlenv-0.1.dist-info/RECORD
yamlenv-0.1.dist-info/WHEEL
