Metadata-Version: 2.0
Name: yamlenv
Version: 0.1
Summary: Interpolate Yaml files with env vars
Home-page: https://github.com/lbolla/yamlenv
Author: Lorenzo Bolla
Author-email: lbolla@gmail.com
License: UNKNOWN
Platform: UNKNOWN
Requires-Dist: PyYAML (>=3.12)
